unclaude/__init__.py
unclaude/__main__.py
unclaude/cli.py
unclaude/config.py
unclaude/context.py
unclaude/hooks.py
unclaude/memory.py
unclaude/onboarding.py
unclaude/agent/__init__.py
unclaude/agent/background.py
unclaude/agent/loop.py
unclaude/agent/planner.py
unclaude/agent/ralph_wiggum.py
unclaude/agent/subagent.py
unclaude/mcp/__init__.py
unclaude/plugins/__init__.py
unclaude/providers/__init__.py
unclaude/providers/llm.py
unclaude/skills/__init__.py
unclaude/tools/__init__.py
unclaude/tools/base.py
unclaude/tools/bash.py
unclaude/tools/browser.py
unclaude/tools/file.py
unclaude/tools/git.py
unclaude/tools/memory.py
unclaude/tools/web.py
unclaude/web/__init__.py
unclaude/web/server.py
unclaude/web/routes/__init__.py
unclaude/web/routes/chat.py
unclaude/web/routes/jobs.py
unclaude/web/routes/mcp.py
unclaude/web/routes/memory.py
unclaude/web/routes/plugins.py
unclaude/web/routes/ralph.py
unclaude/web/routes/settings.py
unclaude/web/routes/skills.py
unclaude/web/static/.gitkeep
unclaude-0.3.1.dist-info/METADATA
unclaude-0.3.1.dist-info/WHEEL
unclaude-0.3.1.dist-info/entry_points.txt
unclaude-0.3.1.dist-info/licenses/LICENSE
unclaude-0.3.1.dist-info/RECORD
