Metadata-Version: 2.4
Name: unclaude
Version: 0.3.1
Summary: Open Source Model-Independent Alternative to Claude Code
Author: UnClaude Contributors
License-Expression: Apache-2.0
License-File: LICENSE
Keywords: agentic,ai,cli,coding-assistant,llm
Classifier: Development Status :: 3 - Alpha
Classifier: Environment :: Console
Classifier: Intended Audience :: Developers
Classifier: License :: OSI Approved :: Apache Software License
Classifier: Programming Language :: Python :: 3.11
Classifier: Programming Language :: Python :: 3.12
Classifier: Topic :: Software Development :: Code Generators
Requires-Python: >=3.11
Requires-Dist: httpx>=0.25.0
Requires-Dist: litellm>=1.56.0
Requires-Dist: pydantic-settings>=2.0.0
Requires-Dist: pydantic>=2.0.0
Requires-Dist: pyyaml>=6.0
Requires-Dist: rich>=13.0.0
Requires-Dist: typer>=0.9.0
Provides-Extra: dev
Requires-Dist: mypy>=1.0.0; extra == 'dev'
Requires-Dist: pytest-asyncio>=0.21.0; extra == 'dev'
Requires-Dist: pytest>=7.0.0; extra == 'dev'
Requires-Dist: ruff>=0.1.0; extra == 'dev'
Provides-Extra: memory
Requires-Dist: chromadb>=0.4.0; extra == 'memory'
Provides-Extra: web
Requires-Dist: fastapi>=0.100.0; extra == 'web'
Requires-Dist: uvicorn>=0.23.0; extra == 'web'
Requires-Dist: websockets>=11.0; extra == 'web'
